ssdeep/_build.py
ssdeep/__about__.py
ssdeep/__init__.py
ssdeep/_libfuzzy.abi3.so
thoth_ssdeep.libs/libfuzzy-681648f0.so.2
thoth_ssdeep-3.4.1.dist-info/RECORD
thoth_ssdeep-3.4.1.dist-info/LICENSE
thoth_ssdeep-3.4.1.dist-info/WHEEL
thoth_ssdeep-3.4.1.dist-info/METADATA
thoth_ssdeep-3.4.1.dist-info/top_level.txt
