Metadata-Version: 2.1
Name: thoth-ssdeep
Version: 3.4.1
Summary: Python wrapper for the ssdeep library
Home-page: http://github.com/DinoTools/python-ssdeep
Author: PhiBo (DinoTools)
License: LGPLv3+
Keywords: ssdeep
Classifier: Development Status :: 5 - Production/Stable
Classifier: Intended Audience :: Developers
Classifier: License :: OSI Approved :: GNU Lesser General Public License v3 or later (LGPLv3+)
Classifier: Operating System :: OS Independent
Classifier: Programming Language :: Python
Classifier: Programming Language :: Python :: 3.6
Classifier: Programming Language :: Python :: 3.7
Classifier: Programming Language :: Python :: 3.8
Classifier: Programming Language :: Python :: 3.9
Classifier: Programming Language :: Python :: 3.10
Classifier: Programming Language :: Python :: Implementation :: CPython
Classifier: Programming Language :: Python :: Implementation :: PyPy
Classifier: Topic :: Software Development :: Libraries :: Python Modules
License-File: LICENSE
Requires-Dist: cffi >=1.0.0
Provides-Extra: docstest
Requires-Dist: doc8 ; extra == 'docstest'
Requires-Dist: readme-renderer >=16.0 ; extra == 'docstest'
Requires-Dist: sphinx ; extra == 'docstest'
Requires-Dist: sphinx-rtd-theme ; extra == 'docstest'
